dottree/__init__.py
license
dottree-0.1.3.dist-info/license
dottree-0.1.3.dist-info/WHEEL
dottree-0.1.3.dist-info/METADATA
dottree-0.1.3.dist-info/RECORD
