Metadata-Version: 2.1
Name: dottree
Version: 0.1.3
Summary: 
Home-page: https://github.com/gitbackspacer/dottree
License: MIT
Keywords: markdown,tree,dict
Author: Jitender
Author-email: gitbackspacer@gmail.com
Classifier: Environment :: Console
Classifier: Framework :: Flake8
Classifier: License :: OSI Approved :: MIT License
Classifier: Operating System :: OS Independent
Classifier: Programming Language :: Python :: 2
Classifier: Programming Language :: Python :: 2.7
Classifier: Programming Language :: Python :: 3
Classifier: Programming Language :: Python :: 3.4
Classifier: Programming Language :: Python :: 3.5
Classifier: Programming Language :: Python :: 3.6
Classifier: Programming Language :: Python :: 3.7
Classifier: Programming Language :: Python :: 3.8
Classifier: Topic :: Software Development :: Documentation
Classifier: Topic :: Software Development :: Libraries :: Python Modules
Classifier: Topic :: Software Development :: Quality Assurance
Project-URL: Repository, https://github.com/gitbackspacer/dottree
